react/__init__.py
react/utils.py
react_fmri-0.1.7.post1.data/scripts/react
react_fmri-0.1.7.post1.data/scripts/react_masks
react_fmri-0.1.7.post1.data/scripts/react_normalize
react_fmri-0.1.7.post1.data/scripts/react_prova.py
react_fmri-0.1.7.post1.dist-info/LICENSE
react_fmri-0.1.7.post1.dist-info/METADATA
react_fmri-0.1.7.post1.dist-info/WHEEL
react_fmri-0.1.7.post1.dist-info/top_level.txt
react_fmri-0.1.7.post1.dist-info/RECORD
