Metadata-Version: 2.1
Name: react-fmri
Version: 0.1.7.post1
Summary: A Python package that implements REACT: Receptor-Enriched Analysis of Functional Connectivity by Targets
Home-page: https://github.com/ottaviadipasquale/react-fmri/
Author: Ottavia Dipasquale, Matteo Frigo
Author-email: ottavia.dipasquale@kcl.ac.uk
License: MIT
Project-URL: Source, https://github.com/ottaviadipasquale/react-fmri
Project-URL: Bug Reports, https://github.com/ottaviadipasquale/react-fmri/issues
Project-URL: Documentation, https://github.com/ottaviadipasquale/react-fmri/blob/main/README.md
Classifier: Intended Audience :: Healthcare Industry
Classifier: Intended Audience :: Science/Research
Classifier: License :: OSI Approved :: MIT License
Classifier: Programming Language :: Python :: 3
Classifier: Development Status :: 4 - Beta
Classifier: Topic :: Scientific/Engineering :: Image Processing
Classifier: Topic :: Scientific/Engineering :: Medical Science Apps.
Requires-Python: >=3
License-File: LICENSE
Requires-Dist: numpy (>=1.15)
Requires-Dist: scipy (>=0.19.1)
Requires-Dist: nibabel (>=3.0.0)
Requires-Dist: scikit-learn (>=0.22)
